memkit/__init__.py
memkit/memory.py
memkit/utils.py
memkit-1.1.1.dist-info/LICENSE
memkit-1.1.1.dist-info/METADATA
memkit-1.1.1.dist-info/WHEEL
memkit-1.1.1.dist-info/top_level.txt
memkit-1.1.1.dist-info/RECORD
