Metadata-Version: 2.1
Name: memkit
Version: 1.1.1
Summary: Memkit is game hacking library for Direct Memory Access (DMA) 
Home-page: https://github.com/0x01code/memkit
Author: 0x01code
Author-email: admin@0x01code.com
License: MIT
License-File: LICENSE
Requires-Dist: memprocfs
Requires-Dist: keystone-engine
